<?xml version="1.0" encoding="utf-8" ?>
<dwsync>
<file name="calendar.css" server="70.39.250.251" local="131541930617322895" remote="131541930600000000" Dst="2" />
<file name="print.css" server="70.39.250.251" local="131527412247826322" remote="131527411800000000" Dst="2" />
<file name="calendarview.css" server="70.39.250.251" local="131529753684511973" remote="131529753600000000" Dst="2" />
<file name="nav.css" server="70.39.250.251" local="131526517870062356" remote="131526510600000000" Dst="2" />
<file name="directory.css" server="70.39.250.251" local="131526517866797765" remote="131526510600000000" Dst="2" />
<file name="docs.css" server="70.39.250.251" local="131472922555989787" remote="131472922200000000" Dst="2" />
<file name="bootstrap.min.css" server="70.39.250.251" local="131526517859532876" remote="131526510600000000" Dst="2" />
<file name="calendar - Copy.css" server="70.39.250.251" local="131526517862806474" remote="131526510600000000" Dst="2" />
<file name="directoryDEV.css" server="70.39.250.251" local="131526517867829699" remote="131526510600000000" Dst="2" />
<file name="schedule.css" server="70.39.250.251" local="131526517872003425" remote="131526510600000000" Dst="2" />
<file name="print_1.css" server="70.39.250.251" local="131534374194738814" remote="131534373600000000" Dst="2" />
</dwsync>